README.md
setup.py
doubaninfo/__init__.py
doubaninfo/douban_book.py
doubaninfo/douban_movie.py
doubaninfo/doubaninfo.py
doubaninfo/main.py
doubaninfo.egg-info/PKG-INFO
doubaninfo.egg-info/SOURCES.txt
doubaninfo.egg-info/dependency_links.txt
doubaninfo.egg-info/entry_points.txt
doubaninfo.egg-info/requires.txt
doubaninfo.egg-info/top_level.txt