Metadata-Version: 2.1
Name: doubaninfo
Version: 0.0.12
Summary: Get douabn information to a summary text.
Home-page: https://github.com/dongshuyan/doubaninfo
Author: sauterne
Author-email: ssauterne@qq.com
License: MIT Licence
Keywords: pip,doubaninfo,douban,movie,book,PTGen,private tracker,PT
Platform: any
Requires-Python: >=3.7.0
